monarchmoney/__init__.py
monarchmoney/monarchmoney.py
monarchmoneycommunity-1.2.0.dist-info/METADATA
monarchmoneycommunity-1.2.0.dist-info/WHEEL
monarchmoneycommunity-1.2.0.dist-info/top_level.txt
monarchmoneycommunity-1.2.0.dist-info/RECORD
