Metadata-Version: 2.4
Name: monarchmoneycommunity
Version: 1.2.0
Summary: Monarch Money API for Python
Home-page: https://github.com/bradleyseanf/monarchmoneycommunity
Author: bradleyseanf
Author-email: bradleyseanf@users.noreply.github.com
License: MIT
Keywords: monarch money,financial,money,personal finance
Platform: any
Classifier: Development Status :: 4 - Beta
Classifier: Intended Audience :: Developers
Classifier: Intended Audience :: Financial and Insurance Industry
Classifier: License :: OSI Approved :: MIT License
Classifier: Topic :: Office/Business :: Financial
Requires-Dist: aiohttp>=3.8.4
Requires-Dist: gql>=4.0
Requires-Dist: oathtool>=2.3.1
Dynamic: author
Dynamic: author-email
Dynamic: classifier
Dynamic: description
Dynamic: description-content-type
Dynamic: home-page
Dynamic: keywords
Dynamic: license
Dynamic: platform
Dynamic: requires-dist
Dynamic: summary
